adsx/.DS_Store
adsx/__init__.py
adsx/main.py
adsx/systemd.py
adsx/__pycache__/__init__.cpython-310.pyc
adsx/__pycache__/main.cpython-310.pyc
adsx-1.0.9.dist-info/METADATA
adsx-1.0.9.dist-info/WHEEL
adsx-1.0.9.dist-info/entry_points.txt
adsx-1.0.9.dist-info/top_level.txt
adsx-1.0.9.dist-info/RECORD
