Metadata-Version: 2.4
Name: adsx
Version: 1.0.9
Summary: no cpatua
Requires-Dist: telethon
Requires-Dist: python-telegram-bot==20.7
